neuropixel.py
spikeglx.py
ibl_neuropixel-1.9.3.dist-info/licenses/LICENSE
ibldsp/__init__.py
ibldsp/cadzow.py
ibldsp/cuda_tools.py
ibldsp/destripe_gpu.py
ibldsp/filter_gpu.py
ibldsp/fourier.py
ibldsp/icsd.py
ibldsp/plots.py
ibldsp/raw_metrics.py
ibldsp/smooth.py
ibldsp/spiketrains.py
ibldsp/utils.py
ibldsp/voltage.py
ibldsp/waveform_extraction.py
ibldsp/waveforms.py
neurowaveforms/__init__.py
neurowaveforms/model.py
tests/integration/__init__.py
tests/integration/csd_experiments.py
tests/integration/test_destripe.py
tests/unit/__init__.py
tests/unit/test_cadzow.py
tests/unit/test_ephys_np2.py
tests/unit/test_neuropixel.py
tests/unit/test_plots.py
tests/unit/test_spikeglx.py
tests/unit/test_utils.py
tests/unit/test_voltage.py
tests/unit/test_waveforms.py
ibl_neuropixel-1.9.3.dist-info/METADATA
ibl_neuropixel-1.9.3.dist-info/WHEEL
ibl_neuropixel-1.9.3.dist-info/top_level.txt
ibl_neuropixel-1.9.3.dist-info/RECORD
