Metadata-Version: 2.4
Name: ibl-neuropixel
Version: 1.9.3
Summary: Collection of tools for Neuropixel 1.0 and 2.0 probes data
Home-page: https://github.com/int-brain-lab/ibl-neuropixel
Author: The International Brain Laboratory
Project-URL: Bug Tracker, https://github.com/int-brain-lab/ibl-neuropixel/issues
Classifier: Programming Language :: Python :: 3
Classifier: License :: OSI Approved :: MIT License
Classifier: Operating System :: OS Independent
Requires-Python: >=3.10
License-File: LICENSE
Requires-Dist: iblutil>=1.7.0
Requires-Dist: joblib
Requires-Dist: matplotlib
Requires-Dist: mtscomp
Requires-Dist: numpy>=1.21.6
Requires-Dist: ONE-api>=2.11.0
Requires-Dist: pandas
Requires-Dist: scipy>=1.11
Dynamic: author
Dynamic: classifier
Dynamic: description
Dynamic: description-content-type
Dynamic: home-page
Dynamic: license-file
Dynamic: project-url
Dynamic: requires-dist
Dynamic: requires-python
Dynamic: summary
